odoo8_addon_base_import_security_group-8.0.1.0.0-py2.7-nspkg.pth
odoo_addons/base_import_security_group/__openerp__.py
odoo_addons/base_import_security_group/hooks.py
odoo_addons/base_import_security_group/__init__.py
odoo_addons/base_import_security_group/README.rst
odoo_addons/base_import_security_group/security/res_groups.xml
odoo_addons/base_import_security_group/i18n/pt.po
odoo_addons/base_import_security_group/i18n/it.po
odoo_addons/base_import_security_group/i18n/es.po
odoo_addons/base_import_security_group/i18n/gl.po
odoo_addons/base_import_security_group/i18n/ca.po
odoo_addons/base_import_security_group/i18n/fr.po
odoo_addons/base_import_security_group/i18n/sk.po
odoo_addons/base_import_security_group/views/base_import.xml
odoo_addons/base_import_security_group/tests/__init__.py
odoo_addons/base_import_security_group/tests/test_base_import_security_group.py
odoo_addons/base_import_security_group/static/description/icon.svg
odoo_addons/base_import_security_group/static/description/icon.png
odoo_addons/base_import_security_group/static/src/js/import.js
odoo_addons/base_import_security_group/static/src/xml/base_import_security_group.xml
odoo8_addon_base_import_security_group-8.0.1.0.0.dist-info/top_level.txt
odoo8_addon_base_import_security_group-8.0.1.0.0.dist-info/WHEEL
odoo8_addon_base_import_security_group-8.0.1.0.0.dist-info/RECORD
odoo8_addon_base_import_security_group-8.0.1.0.0.dist-info/metadata.json
odoo8_addon_base_import_security_group-8.0.1.0.0.dist-info/DESCRIPTION.rst
odoo8_addon_base_import_security_group-8.0.1.0.0.dist-info/METADATA
odoo8_addon_base_import_security_group-8.0.1.0.0.dist-info/namespace_packages.txt
