Metadata-Version: 2.0
Name: odoo8-addon-base-import-security-group
Version: 8.0.1.0.0
Summary: Group-based permissions for importing CSV files
Home-page: https://github.com/OCA/server-tools
Author: Odoo Community Association (OCA), Alejandro Santana <alejandrosantana@anubia.es>
Author-email: support@odoo-community.org
License: AGPL-3
Platform: UNKNOWN
Requires-Dist: odoo (<9.0a,>=8.0a)
Classifier: Programming Language :: Python :: 2.7
Classifier: Framework :: Odoo
Classifier: License :: OSI Approved :: GNU Affero General Public License v3
